finalsa/ses/client/__init__.py
finalsa/ses/client/py.typed
finalsa/ses/client/client/__init__.py
finalsa/ses/client/client/client.py
finalsa/ses/client/interface/__init__.py
finalsa/ses/client/interface/client.py
finalsa/ses/client/tests/__init__.py
finalsa/ses/client/tests/client.py
finalsa/ses/client/tests/email.py
finalsa_ses_client-0.0.2.data/data/LICENSE.md
finalsa_ses_client-0.0.2.dist-info/LICENSE.md
finalsa_ses_client-0.0.2.dist-info/METADATA
finalsa_ses_client-0.0.2.dist-info/WHEEL
finalsa_ses_client-0.0.2.dist-info/top_level.txt
finalsa_ses_client-0.0.2.dist-info/zip-safe
finalsa_ses_client-0.0.2.dist-info/RECORD
