Metadata-Version: 2.1
Name: finalsa-ses-client
Version: 0.0.2
Summary: An utils package for using s3
Home-page: https://github.com/finalsa/finalsa-ses-client
Author: Luis Jimenez
Author-email: luis@finalsa.com
License: MIT
Keywords: ses
Classifier: Intended Audience :: Developers
Classifier: License :: OSI Approved :: BSD License
Classifier: Operating System :: OS Independent
Classifier: Topic :: Internet :: WWW/HTTP
Classifier: Programming Language :: Python :: 3
Classifier: Programming Language :: Python :: 3.7
Classifier: Programming Language :: Python :: 3.8
Classifier: Programming Language :: Python :: 3.9
Classifier: Programming Language :: Python :: 3.10
Requires-Python: >=3.10
License-File: LICENSE.md
Requires-Dist: boto3 >=1.20.3
